pyhopf/__init__.py
pyhopf/hopfindex.py
pyhopf-1.0.1.dist-info/LICENSE
pyhopf-1.0.1.dist-info/WHEEL
pyhopf-1.0.1.dist-info/METADATA
pyhopf-1.0.1.dist-info/RECORD
