Metadata-Version: 2.3
Name: pyhopf
Version: 1.0.1
Summary: Small Python package to calculate the Hopf index of vector fields from finite-difference simulations.
Author: Ross Knapman, Maria Azhar, Alessandro Pignedoli, Louis Gallard, Riccardo Hertel, Jonathan Leliaert, Karin Everschor-Sitte
Requires-Python: >=3.8
Classifier: Programming Language :: Python :: 3
Classifier: License :: OSI Approved :: GNU General Public License v3 (GPLv3)
Classifier: Operating System :: OS Independent
Classifier: Intended Audience :: Education
Classifier: Intended Audience :: Developers
Classifier: Intended Audience :: Science/Research
Classifier: Topic :: Scientific/Engineering :: Physics
Classifier: Topic :: Scientific/Engineering :: Mathematics
Requires-Dist: numpy
Project-URL: Homepage, https://git.uni-due.de/twist-external/numericalhopfindexcalculation/numericalhopfindexcalculation_pythonhopfindex
Project-URL: Issues, https://git.uni-due.de/twist-external/numericalhopfindexcalculation/numericalhopfindexcalculation_pythonhopfindex/-/issues
